LICENSE.txt
MANIFEST.in
README.txt
setup.cfg
setup.py
minecraftia/Minecraftia.ttf
minecraftia/readme.txt
minecraftmap/__init__.py
minecraftmap.egg-info/PKG-INFO
minecraftmap.egg-info/SOURCES.txt
minecraftmap.egg-info/dependency_links.txt
minecraftmap.egg-info/requires.txt
minecraftmap.egg-info/top_level.txt