Metadata-Version: 1.1
Name: minecraftmap
Version: 0.2
Summary: Minecraft Map Reader/Writer
Home-page: https://github.com/spookymushroom/minecraftmap/
Author: Michael Korotkov
Author-email: github.spookymushroom@gmail.com
License: Copyright (c) 2016 Michael Korotkov and contributors
